LICENSE
LICENSE.pybind_python_example
MANIFEST.in
README.rst
requirements.txt
setup.py
clast/__init__.py
clast.egg-info/PKG-INFO
clast.egg-info/SOURCES.txt
clast.egg-info/dependency_links.txt
clast.egg-info/not-zip-safe
clast.egg-info/requires.txt
clast.egg-info/top_level.txt
src/ast_matcher_bindings.cpp
src/internal.h
src/matcher_bindings.cpp
src/modulemain.cpp
src/pyclast.h
src/toolmain.cpp
src/381/00_autogen_enums.cpp
src/381/01_autogen_classes.cpp
src/381/02_autogen_classes.cpp
src/381/03_autogen_classes.cpp
src/381/04_autogen_classes.cpp
src/381/autogen_classes.cpp
src/381/autogen_dyntypenode.cpp
src/381/intermediate.json
src/390/00_autogen_enums.cpp
src/390/01_autogen_classes.cpp
src/390/02_autogen_classes.cpp
src/390/03_autogen_classes.cpp
src/390/04_autogen_classes.cpp
src/390/05_autogen_classes.cpp
src/390/autogen_classes.cpp
src/390/autogen_dyntypenode.cpp
src/390/intermediate.json
test/test_matcher.py