Metadata-Version: 1.1
Name: clast
Version: 0.0.1rc0
Summary: Python bindings for the unstable interface of the Clang AST Matchers library
Home-page: http://github.com/AndrewWalker/clast
Author: Andrew Walker
Author-email: walker.ab@gmail.com
License: MIT
Platform: UNKNOWN
Classifier: Development Status :: 2 - Pre-Alpha
Classifier: Intended Audience :: Developers
Classifier: License :: OSI Approved :: MIT License
Classifier: Natural Language :: English
Classifier: Programming Language :: Python :: 2
Classifier: Programming Language :: Python :: 3
Classifier: Programming Language :: Python :: 2.7
Classifier: Programming Language :: Python :: 3.5
Classifier: Operating System :: POSIX :: Linux
Classifier: Topic :: Software Development :: Code Generators
